fhir_aggregator/__init__.py
fhir_aggregator/cli/__init__.py
fhir_aggregator/cli/click_util.py
fhir_aggregator/cli/credentials_cli.py
fhir_aggregator/cli/metrics_cli.py
fhir_aggregator/cli/normalize_cli.py
fhir_aggregator/cli/search_cli.py
fhir_aggregator/cli/servers_cli.py
fhir_aggregator/client/__init__.py
fhir_aggregator/client/smart_auth.py
tests/__init__.py
tests/integration/__init__.py
tests/integration/conftest.py
tests/integration/test_client.py
tests/integration/test_simple_pipelines.py
tests/unit/__init__.py
tests/unit/test_capability_statement.py
tests/unit/test_cli.py
tests/unit/test_credentials.py
tests/unit/test_operation_definition.py
tests/unit/test_research_study.py
fhir_aggregator-0.2rc2.dist-info/LICENSE
fhir_aggregator-0.2rc2.dist-info/METADATA
fhir_aggregator-0.2rc2.dist-info/WHEEL
fhir_aggregator-0.2rc2.dist-info/entry_points.txt
fhir_aggregator-0.2rc2.dist-info/top_level.txt
fhir_aggregator-0.2rc2.dist-info/RECORD
