Metadata-Version: 2.1
Name: fhir-aggregator
Version: 0.2rc2
License-File: LICENSE
Requires-Dist: requests
Requires-Dist: click
Requires-Dist: PyYAML
Requires-Dist: fhirclient
Requires-Dist: pydantic
Requires-Dist: pyfunctional
Requires-Dist: pandas
Requires-Dist: upsetplot
Requires-Dist: inflection
